[
  {
    "id": 65622692,
    "name": "Y-Dragon Head",
    "type": "Union Effect Monster",
    "desc": "Once per turn, you can either: Target 1 \"X-Head Cannon\" you control; equip this card to that target, OR: Unequip this card and Special Summon it. A monster equipped with this card gains 400 ATK/DEF, also if the equipped monster would be destroyed by battle or card effect, destroy this card instead.",
    "atk": 1500,
    "def": 1600,
    "level": 4,
    "race": "Machine",
    "attribute": "LIGHT",
    "scale": "",
    "archetype": "ABC",
    "linkval": "",
    "linkmarkers": "",
    "image_url": "https://images.ygoprodeck.com/images/cards/65622692.jpg",
    "image_url_small": "https://images.ygoprodeck.com/images/cards_small/65622692.jpg",
    "ban_tcg": "",
    "ban_ocg": "",
    "ban_goat": "",
    "staple": "",
    "views": 176199,
    "viewsweek": 26,
    "upvotes": 7,
    "downvotes": 0,
    "formats": "GOAT|OCG GOAT|Duel Links|Speed Duel|Common Charity|Edison|TCG|OCG|Master Duel",
    "treated_as": "",
    "tcg_date": "2003-10-10",
    "ocg_date": "2002-07-18",
    "konami_id": 5552,
    "has_effect": 1
  },
  {
    "id": 6355563,
    "name": "Y-Dragon Yearhead",
    "type": "Union Effect Monster",
    "desc": "If this card is Special Summoned: You can equip 1 Level 4 LIGHT Machine monster from your hand or GY to this card, also you cannot Special Summon from the Extra Deck for the rest of this turn, except LIGHT monsters. Once per turn, you can either: Target 1 Machine monster you control; equip this card to that target, OR: Unequip this card and Special Summon it. If the equipped monster would be destroyed by battle or card effect, destroy this card instead.",
    "atk": 1500,
    "def": 1600,
    "level": 4,
    "race": "Machine",
    "attribute": "LIGHT",
    "scale": "",
    "archetype": "A-to-Z",
    "linkval": "",
    "linkmarkers": "",
    "image_url": "https://images.ygoprodeck.com/images/cards/6355563.jpg",
    "image_url_small": "https://images.ygoprodeck.com/images/cards_small/6355563.jpg",
    "ban_tcg": "",
    "ban_ocg": "",
    "ban_goat": "",
    "staple": "",
    "views": 15682,
    "viewsweek": 0,
    "upvotes": 0,
    "downvotes": 0,
    "formats": "OCG",
    "treated_as": "",
    "tcg_date": "",
    "ocg_date": "2024-05-25",
    "konami_id": "",
    "has_effect": 1
  },
  {
    "id": 25119460,
    "name": "YZ-Tank Dragon",
    "type": "Fusion Monster",
    "desc": "Y-Dragon Head\" + \"Z-Metal Tank\"\nMust first be Special Summoned (from your Extra Deck) by banishing the above cards you control. (You do not use \"Polymerization\".) Cannot be Special Summoned from the Graveyard. You can discard 1 card, then target 1 face-down monster your opponent controls; destroy that target.",
    "atk": 2100,
    "def": 2200,
    "level": 6,
    "race": "Machine",
    "attribute": "LIGHT",
    "scale": "",
    "archetype": "ABC",
    "linkval": "",
    "linkmarkers": "",
    "image_url": "https://images.ygoprodeck.com/images/cards/25119460.jpg",
    "image_url_small": "https://images.ygoprodeck.com/images/cards_small/25119460.jpg",
    "ban_tcg": "",
    "ban_ocg": "",
    "ban_goat": "",
    "staple": "",
    "views": 87244,
    "viewsweek": 0,
    "upvotes": 4,
    "downvotes": 0,
    "formats": "GOAT|OCG GOAT|Duel Links|Speed Duel|Common Charity|Edison|TCG|OCG|Master Duel",
    "treated_as": "",
    "tcg_date": "2003-10-10",
    "ocg_date": "2002-07-18",
    "konami_id": 5626,
    "has_effect": 1
  },
  {
    "id": 29380133,
    "name": "Yado Karu",
    "type": "Effect Monster",
    "desc": "When this card is changed from Attack Position to Defense Position, you can place any number of cards from your hand at the bottom of your Deck in any order you desire.",
    "atk": 900,
    "def": 1700,
    "level": 4,
    "race": "Aqua",
    "attribute": "WATER",
    "scale": "",
    "archetype": "",
    "linkval": "",
    "linkmarkers": "",
    "image_url": "https://images.ygoprodeck.com/images/cards/29380133.jpg",
    "image_url_small": "https://images.ygoprodeck.com/images/cards_small/29380133.jpg",
    "ban_tcg": "",
    "ban_ocg": "",
    "ban_goat": "",
    "staple": "",
    "views": 124827,
    "viewsweek": 0,
    "upvotes": 3,
    "downvotes": 3,
    "formats": "GOAT|OCG GOAT|Duel Links|Common Charity|Edison|TCG|OCG|Master Duel",
    "treated_as": "",
    "tcg_date": "2002-06-26",
    "ocg_date": "2000-03-01",
    "konami_id": 4503,
    "has_effect": 1
  },
  {
    "id": 13298352,
    "name": "Yaguramaru the Armor Ninja",
    "type": "Fusion Monster",
    "desc": "2 \"Ninja\" monsters with different Types\nMust first be either Fusion Summoned, or Special Summoned from your Extra Deck by Tributing the above cards. If this card is Special Summoned or flipped face-up: You can banish 1 other \"Ninja\" or \"Ninjitsu Art\" card from your hand, GY, or face-up field, then target 1 card on the field; banish it. You can only use this effect of \"Yaguramaru the Armor Ninja\" once per turn.",
    "atk": 2000,
    "def": 2000,
    "level": 5,
    "race": "Machine",
    "attribute": "DARK",
    "scale": "",
    "archetype": "Ninja",
    "linkval": "",
    "linkmarkers": "",
    "image_url": "https://images.ygoprodeck.com/images/cards/13298352.jpg",
    "image_url_small": "https://images.ygoprodeck.com/images/cards_small/13298352.jpg",
    "ban_tcg": "",
    "ban_ocg": "",
    "ban_goat": "",
    "staple": "",
    "views": 42798,
    "viewsweek": 0,
    "upvotes": 0,
    "downvotes": 0,
    "formats": "Common Charity|TCG|OCG|Master Duel",
    "treated_as": "",
    "tcg_date": "2023-02-09",
    "ocg_date": "2022-10-15",
    "konami_id": 18181,
    "has_effect": 1
  },
  {
    "id": 10315429,
    "name": "Yaiba Robo",
    "type": "Normal Monster",
    "desc": "A cubical machine equipped with cutting blades for shredding an opponent to mincemeat.",
    "atk": 1000,
    "def": 1300,
    "level": 4,
    "race": "Machine",
    "attribute": "DARK",
    "scale": "",
    "archetype": "",
    "linkval": "",
    "linkmarkers": "",
    "image_url": "https://images.ygoprodeck.com/images/cards/10315429.jpg",
    "image_url_small": "https://images.ygoprodeck.com/images/cards_small/10315429.jpg",
    "ban_tcg": "",
    "ban_ocg": "",
    "ban_goat": "",
    "staple": "",
    "views": 8246,
    "viewsweek": 0,
    "upvotes": 4,
    "downvotes": 3,
    "formats": "OCG GOAT|Duel Links|Speed Duel|Common Charity|TCG|OCG|Master Duel",
    "treated_as": "",
    "tcg_date": "2020-05-14",
    "ocg_date": "1999-09-23",
    "konami_id": 4412,
    "has_effect": 0
  },
  {
    "id": 10852583,
    "name": "Yajiro Invader",
    "type": "Effect Monster",
    "desc": "If this card is Normal or Special Summoned to a zone that is not the center Main Monster Zone, destroy this card. Once per turn: You can move this card to an unused adjacent Main Monster Zone. Each time exactly 1 monster is Normal or Special Summoned, to your opponent's field: Move this card to the adjacent Main Monster Zone closer to that opponent's monster, then destroy all other cards in this card's column.",
    "atk": 2200,
    "def": 0,
    "level": 5,
    "race": "Reptile",
    "attribute": "DARK",
    "scale": "",
    "archetype": "",
    "linkval": "",
    "linkmarkers": "",
    "image_url": "https://images.ygoprodeck.com/images/cards/10852583.jpg",
    "image_url_small": "https://images.ygoprodeck.com/images/cards_small/10852583.jpg",
    "ban_tcg": "",
    "ban_ocg": "",
    "ban_goat": "",
    "staple": "",
    "views": 17364,
    "viewsweek": 0,
    "upvotes": 5,
    "downvotes": 1,
    "formats": "Common Charity|TCG|OCG|Master Duel",
    "treated_as": "",
    "tcg_date": "2018-05-03",
    "ocg_date": "2018-01-13",
    "konami_id": 13585,
    "has_effect": 1
  },
  {
    "id": 94215860,
    "name": "Yaksha",
    "type": "Spirit Monster",
    "desc": "Cannot be Special Summoned. During the End Phase of the turn this card is Normal Summoned or flipped face-up: Return it to the hand. When this card is Normal Summoned or flipped face-up: You can target 1 Spell/Trap Card your opponent controls; return that target to the hand.",
    "atk": 1900,
    "def": 1500,
    "level": 4,
    "race": "Fairy",
    "attribute": "WATER",
    "scale": "",
    "archetype": "",
    "linkval": "",
    "linkmarkers": "",
    "image_url": "https://images.ygoprodeck.com/images/cards/94215860.jpg",
    "image_url_small": "https://images.ygoprodeck.com/images/cards_small/94215860.jpg",
    "ban_tcg": "",
    "ban_ocg": "",
    "ban_goat": "",
    "staple": "",
    "views": 25670,
    "viewsweek": 0,
    "upvotes": 2,
    "downvotes": 0,
    "formats": "Duel Links|Common Charity|TCG|OCG|Master Duel",
    "treated_as": "",
    "tcg_date": "2011-02-08",
    "ocg_date": "2010-11-13",
    "konami_id": 9328,
    "has_effect": 1
  },
  {
    "id": 90583279,
    "name": "Yakusa, Lord of the Eight Thunders",
    "type": "Effect Monster",
    "desc": "You can Special Summon this card (from your hand) by banishing 1 Level/Rank 8 monster from your GY. You can target 1 Level/Rank 8 Ritual, Fusion, Synchro, or Xyz Monster in your GY; shuffle it into the Deck, then apply the following effect depending on the returned monster's card type.\n● Ritual/Fusion: Draw 1 card.\n● Synchro/Xyz: This card gains 1000 ATK.\nYou can only use this effect of \"Yakusa, Lord of the Eight Thunders\" once per turn.",
    "atk": 2000,
    "def": 2000,
    "level": 8,
    "race": "Wyrm",
    "attribute": "LIGHT",
    "scale": "",
    "archetype": "",
    "linkval": "",
    "linkmarkers": "",
    "image_url": "https://images.ygoprodeck.com/images/cards/90583279.jpg",
    "image_url_small": "https://images.ygoprodeck.com/images/cards_small/90583279.jpg",
    "ban_tcg": "",
    "ban_ocg": "",
    "ban_goat": "",
    "staple": "",
    "views": 16741,
    "viewsweek": 0,
    "upvotes": 1,
    "downvotes": 0,
    "formats": "TCG|OCG|Master Duel",
    "treated_as": "",
    "tcg_date": "2022-05-19",
    "ocg_date": "2021-12-21",
    "konami_id": 17267,
    "has_effect": 1
  },
  {
    "id": 70345785,
    "name": "Yamadron",
    "type": "Normal Monster",
    "desc": "This monster has three fire-breathing heads and can form a sea of blazing flames.",
    "atk": 1600,
    "def": 1800,
    "level": 5,
    "race": "Dragon",
    "attribute": "FIRE",
    "scale": "",
    "archetype": "",
    "linkval": "",
    "linkmarkers": "",
    "image_url": "https://images.ygoprodeck.com/images/cards/70345785.jpg",
    "image_url_small": "https://images.ygoprodeck.com/images/cards_small/70345785.jpg",
    "ban_tcg": "",
    "ban_ocg": "",
    "ban_goat": "",
    "staple": "",
    "views": 15767,
    "viewsweek": 0,
    "upvotes": 7,
    "downvotes": 2,
    "formats": "GOAT|OCG GOAT|Duel Links|Common Charity|Edison|TCG|OCG|Master Duel",
    "treated_as": "",
    "tcg_date": "2002-12-20",
    "ocg_date": "1999-06-01",
    "konami_id": 4363,
    "has_effect": 0
  },
  {
    "id": 76862289,
    "name": "Yamata Dragon",
    "type": "Spirit Monster",
    "desc": "This card cannot be Special Summoned. This card returns to its owner's hand during the End Phase of the turn it is Normal Summoned or flipped face-up. When this card inflicts Battle Damage to your opponent, draw cards until you have 5 cards in your hand.",
    "atk": 2600,
    "def": 3100,
    "level": 7,
    "race": "Dragon",
    "attribute": "FIRE",
    "scale": "",
    "archetype": "",
    "linkval": "",
    "linkmarkers": "",
    "image_url": "https://images.ygoprodeck.com/images/cards/76862289.jpg",
    "image_url_small": "https://images.ygoprodeck.com/images/cards_small/76862289.jpg",
    "ban_tcg": "",
    "ban_ocg": "",
    "ban_goat": "",
    "staple": "",
    "views": 67638,
    "viewsweek": 0,
    "upvotes": 8,
    "downvotes": 2,
    "formats": "GOAT|OCG GOAT|Duel Links|Edison|TCG|OCG|Master Duel",
    "treated_as": "",
    "tcg_date": "2003-06-06",
    "ocg_date": "2001-11-29",
    "konami_id": 5377,
    "has_effect": 1
  },
  {
    "id": 4632019,
    "name": "Yamatako Orochi",
    "type": "Tuner Monster",
    "desc": "This card on the field can be treated as a Level 8 monster when used for a Synchro Summon. A Synchro Monster that used this card as material gains this effect based on its original Level.\n● 8 or lower: Gains 800 ATK/DEF.\n● 9 or higher: If this card attacks a Defense Position monster, inflict piercing battle damage.",
    "atk": 0,
    "def": 800,
    "level": 1,
    "race": "Sea Serpent",
    "attribute": "WATER",
    "scale": "",
    "archetype": "",
    "linkval": "",
    "linkmarkers": "",
    "image_url": "https://images.ygoprodeck.com/images/cards/4632019.jpg",
    "image_url_small": "https://images.ygoprodeck.com/images/cards_small/4632019.jpg",
    "ban_tcg": "",
    "ban_ocg": "",
    "ban_goat": "",
    "staple": "",
    "views": 23080,
    "viewsweek": 0,
    "upvotes": 5,
    "downvotes": 0,
    "formats": "Common Charity|TCG|OCG|Master Duel",
    "treated_as": "",
    "tcg_date": "2022-05-19",
    "ocg_date": "2022-01-15",
    "konami_id": 17143,
    "has_effect": 1
  },
  {
    "id": 76704943,
    "name": "Yamatano Dragon Scroll",
    "type": "Normal Monster",
    "desc": "A dragon conjured from the very scroll in which it was depicted.",
    "atk": 900,
    "def": 300,
    "level": 2,
    "race": "Dragon",
    "attribute": "WIND",
    "scale": "",
    "archetype": "",
    "linkval": "",
    "linkmarkers": "",
    "image_url": "https://images.ygoprodeck.com/images/cards/76704943.jpg",
    "image_url_small": "https://images.ygoprodeck.com/images/cards_small/76704943.jpg",
    "ban_tcg": "",
    "ban_ocg": "",
    "ban_goat": "",
    "staple": "",
    "views": 10051,
    "viewsweek": 0,
    "upvotes": 5,
    "downvotes": 3,
    "formats": "OCG GOAT|Duel Links|OCG|Master Duel",
    "treated_as": "",
    "tcg_date": "",
    "ocg_date": "1999-03-01",
    "konami_id": "",
    "has_effect": 0
  },
  {
    "id": 82841979,
    "name": "Yamato-no-Kami",
    "type": "Spirit Monster",
    "desc": "This card cannot be Normal Summoned or Set. This card cannot be Special Summoned except by removing from play 1 Spirit monster from your Graveyard. This card returns to its owner's hand during the End Phase of the turn it is Special Summoned. If this card destroys an opponent's monster by battle, you can destroy 1 Spell or Trap Card your opponent controls.",
    "atk": 2200,
    "def": 1200,
    "level": 6,
    "race": "Warrior",
    "attribute": "DARK",
    "scale": "",
    "archetype": "",
    "linkval": "",
    "linkmarkers": "",
    "image_url": "https://images.ygoprodeck.com/images/cards/82841979.jpg",
    "image_url_small": "https://images.ygoprodeck.com/images/cards_small/82841979.jpg",
    "ban_tcg": "",
    "ban_ocg": "",
    "ban_goat": "",
    "staple": "",
    "views": 34539,
    "viewsweek": 0,
    "upvotes": 6,
    "downvotes": 0,
    "formats": "Duel Links|Edison|TCG|OCG|Master Duel",
    "treated_as": "",
    "tcg_date": "2008-08-09",
    "ocg_date": "2008-04-19",
    "konami_id": 7729,
    "has_effect": 1
  },
  {
    "id": 59197169,
    "name": "Yami",
    "type": "Spell Card",
    "desc": "All Fiend and Spellcaster monsters on the field gain 200 ATK/DEF, also all Fairy monsters on the field lose 200 ATK/DEF.",
    "atk": "",
    "def": "",
    "level": "",
    "race": "Field",
    "attribute": "",
    "scale": "",
    "archetype": "",
    "linkval": "",
    "linkmarkers": "",
    "image_url": "https://images.ygoprodeck.com/images/cards/59197169.jpg",
    "image_url_small": "https://images.ygoprodeck.com/images/cards_small/59197169.jpg",
    "ban_tcg": "",
    "ban_ocg": "",
    "ban_goat": "",
    "staple": "",
    "views": 311767,
    "viewsweek": 0,
    "upvotes": 8,
    "downvotes": 2,
    "formats": "GOAT|Speed Duel|OCG GOAT|Duel Links|Common Charity|Edison|TCG|OCG|Master Duel",
    "treated_as": "",
    "tcg_date": "2002-03-08",
    "ocg_date": "1999-03-06",
    "konami_id": 4341,
    "has_effect": 1
  },
  {
    "id": 24181936,
    "name": "Yaminabe Party",
    "type": "Spell Card",
    "desc": "At the start of your Battle Phase: You can target 1 face-up monster you control; this turn, your opponent chooses the attack target(s) for that monster, also if that monster you control battles an opponent's monster, it gains ATK equal to its original ATK during damage calculation only. You can only use this effect of \"Yaminabe Party\" once per turn.",
    "atk": "",
    "def": "",
    "level": "",
    "race": "Continuous",
    "attribute": "",
    "scale": "",
    "archetype": "",
    "linkval": "",
    "linkmarkers": "",
    "image_url": "https://images.ygoprodeck.com/images/cards/24181936.jpg",
    "image_url_small": "https://images.ygoprodeck.com/images/cards_small/24181936.jpg",
    "ban_tcg": "",
    "ban_ocg": "",
    "ban_goat": "",
    "staple": "",
    "views": 7509,
    "viewsweek": 0,
    "upvotes": 1,
    "downvotes": 0,
    "formats": "TCG|OCG|Master Duel",
    "treated_as": "",
    "tcg_date": "2020-08-06",
    "ocg_date": "2019-12-21",
    "konami_id": 15087,
    "has_effect": 1
  },
  {
    "id": 51474037,
    "name": "Yamorimori",
    "type": "Effect Monster",
    "desc": "You can banish this card from your GY, then target 1 Reptile monster you control and 1 face-up monster your opponent controls, to activate 1 of these effects;\n● Change those monsters to face-down Defense Position.\n● Destroy that monster you control, and if you do, change the ATK of the other monster to 0 until the end of this turn.\nYou can only use this effect of \"Yamorimori\" once per turn.",
    "atk": 0,
    "def": 0,
    "level": 2,
    "race": "Reptile",
    "attribute": "WATER",
    "scale": "",
    "archetype": "",
    "linkval": "",
    "linkmarkers": "",
    "image_url": "https://images.ygoprodeck.com/images/cards/51474037.jpg",
    "image_url_small": "https://images.ygoprodeck.com/images/cards_small/51474037.jpg",
    "ban_tcg": "",
    "ban_ocg": "",
    "ban_goat": "",
    "staple": "",
    "views": 20062,
    "viewsweek": 0,
    "upvotes": 2,
    "downvotes": 1,
    "formats": "Common Charity|TCG|OCG|Master Duel",
    "treated_as": "",
    "tcg_date": "2021-06-03",
    "ocg_date": "2021-01-16",
    "konami_id": 15990,
    "has_effect": 1
  },
  {
    "id": 67249508,
    "name": "Yang Zing Brutality",
    "type": "Trap Card",
    "desc": "If a \"Yang Zing\" monster you control battles an opponent's monster, during damage calculation: Your battling monster's ATK and DEF each become double its original ATK and DEF during that damage calculation only, but it is destroyed at the end of this Damage Step.",
    "atk": "",
    "def": "",
    "level": "",
    "race": "Normal",
    "attribute": "",
    "scale": "",
    "archetype": "Yang Zing",
    "linkval": "",
    "linkmarkers": "",
    "image_url": "https://images.ygoprodeck.com/images/cards/67249508.jpg",
    "image_url_small": "https://images.ygoprodeck.com/images/cards_small/67249508.jpg",
    "ban_tcg": "",
    "ban_ocg": "",
    "ban_goat": "",
    "staple": "",
    "views": 14490,
    "viewsweek": 0,
    "upvotes": 1,
    "downvotes": 1,
    "formats": "Duel Links|Common Charity|TCG|OCG|Master Duel",
    "treated_as": "",
    "tcg_date": "2014-11-06",
    "ocg_date": "2014-07-19",
    "konami_id": 11407,
    "has_effect": 1
  },
  {
    "id": 30398342,
    "name": "Yang Zing Creation",
    "type": "Trap Card",
    "desc": "Once per turn, if a monster(s) you control is destroyed by battle or card effect: You can Special Summon 1 \"Yang Zing\" monster from your Deck. You cannot Special Summon monsters from the Extra Deck, except Synchro Monsters.",
    "atk": "",
    "def": "",
    "level": "",
    "race": "Continuous",
    "attribute": "",
    "scale": "",
    "archetype": "Yang Zing",
    "linkval": "",
    "linkmarkers": "",
    "image_url": "https://images.ygoprodeck.com/images/cards/30398342.jpg",
    "image_url_small": "https://images.ygoprodeck.com/images/cards_small/30398342.jpg",
    "ban_tcg": "",
    "ban_ocg": "",
    "ban_goat": "",
    "staple": "",
    "views": 28655,
    "viewsweek": 0,
    "upvotes": 0,
    "downvotes": 1,
    "formats": "Duel Links|TCG|OCG|Master Duel",
    "treated_as": "",
    "tcg_date": "2014-08-14",
    "ocg_date": "2014-04-19",
    "konami_id": 11283,
    "has_effect": 1
  },
  {
    "id": 17183908,
    "name": "Yang Zing Path",
    "type": "Spell Card",
    "desc": "Target 3 \"Yang Zing\" monsters in your Graveyard; shuffle all 3 into the Deck, then draw 2 cards. You can only activate 1 \"Yang Zing Path\" per turn.",
    "atk": "",
    "def": "",
    "level": "",
    "race": "Normal",
    "attribute": "",
    "scale": "",
    "archetype": "Yang Zing",
    "linkval": "",
    "linkmarkers": "",
    "image_url": "https://images.ygoprodeck.com/images/cards/17183908.jpg",
    "image_url_small": "https://images.ygoprodeck.com/images/cards_small/17183908.jpg",
    "ban_tcg": "",
    "ban_ocg": "",
    "ban_goat": "",
    "staple": "",
    "views": 43638,
    "viewsweek": 0,
    "upvotes": 3,
    "downvotes": 0,
    "formats": "TCG|OCG|Master Duel",
    "treated_as": "",
    "tcg_date": "2014-08-14",
    "ocg_date": "2014-04-19",
    "konami_id": 11270,
    "has_effect": 1
  },
  {
    "id": 43577607,
    "name": "Yang Zing Prana",
    "type": "Spell Card",
    "desc": "This card gains these effects, based on the number of different Attributes the \"Yang Zing\" monsters in your Graveyard have.\n● 2 or more: All \"Yang Zing\" monsters you control gain 500 ATK.\n● 3 or more: If a \"Yang Zing\" monster(s) you control would be destroyed by battle or card effect, you can send this card to the Graveyard instead.\n● 4 or more: Your opponent cannot Set monsters. Change all face-up monsters your opponent controls to Attack Position.\n● 5 or more: You can send this card to the Graveyard; destroy all cards on the field.",
    "atk": "",
    "def": "",
    "level": "",
    "race": "Continuous",
    "attribute": "",
    "scale": "",
    "archetype": "Yang Zing",
    "linkval": "",
    "linkmarkers": "",
    "image_url": "https://images.ygoprodeck.com/images/cards/43577607.jpg",
    "image_url_small": "https://images.ygoprodeck.com/images/cards_small/43577607.jpg",
    "ban_tcg": "",
    "ban_ocg": "",
    "ban_goat": "",
    "staple": "",
    "views": 21277,
    "viewsweek": 0,
    "upvotes": 1,
    "downvotes": 0,
    "formats": "Duel Links|Common Charity|TCG|OCG|Master Duel",
    "treated_as": "",
    "tcg_date": "2014-08-14",
    "ocg_date": "2014-04-19",
    "konami_id": 11271,
    "has_effect": 1
  },
  {
    "id": 77783947,
    "name": "Yang Zing Unleashed",
    "type": "Trap Card",
    "desc": "All monsters your opponent controls must attack, if able. During either player's Main Phase or Battle Phase: You can send this face-up card from your Spell & Trap Zone to the Graveyard; immediately after this effect resolves, Synchro Summon 1 Synchro Monster, using 1 or more \"Yang Zing\" monsters you control as Synchro Materials.",
    "atk": "",
    "def": "",
    "level": "",
    "race": "Continuous",
    "attribute": "",
    "scale": "",
    "archetype": "Yang Zing",
    "linkval": "",
    "linkmarkers": "",
    "image_url": "https://images.ygoprodeck.com/images/cards/77783947.jpg",
    "image_url_small": "https://images.ygoprodeck.com/images/cards_small/77783947.jpg",
    "ban_tcg": "",
    "ban_ocg": "",
    "ban_goat": "",
    "staple": "",
    "views": 25077,
    "viewsweek": 0,
    "upvotes": 0,
    "downvotes": 0,
    "formats": "Common Charity|TCG|OCG|Master Duel",
    "treated_as": "",
    "tcg_date": "2014-08-14",
    "ocg_date": "2014-04-19",
    "konami_id": 11284,
    "has_effect": 1
  },
  {
    "id": 71280811,
    "name": "Yaranzo",
    "type": "Normal Monster",
    "desc": "A treasure box containing a monster that attacks any unwary bandit.",
    "atk": 1300,
    "def": 1500,
    "level": 4,
    "race": "Zombie",
    "attribute": "DARK",
    "scale": "",
    "archetype": "",
    "linkval": "",
    "linkmarkers": "",
    "image_url": "https://images.ygoprodeck.com/images/cards/71280811.jpg",
    "image_url_small": "https://images.ygoprodeck.com/images/cards_small/71280811.jpg",
    "ban_tcg": "",
    "ban_ocg": "",
    "ban_goat": "",
    "staple": "",
    "views": 18707,
    "viewsweek": 0,
    "upvotes": 5,
    "downvotes": 1,
    "formats": "GOAT|OCG GOAT|Duel Links|Common Charity|Edison|TCG|OCG|Master Duel",
    "treated_as": "",
    "tcg_date": "2002-12-20",
    "ocg_date": "1999-06-01",
    "konami_id": 4357,
    "has_effect": 0
  },
  {
    "id": 77714963,
    "name": "Yasha, the Skeletal Mayakashi",
    "type": "Effect Monster",
    "desc": "You can discard 1 other \"Mayakashi\" monster; Special Summon this card from your hand. You can only use this effect of \"Yasha, the Skeletal Mayakashi\" once per turn. You cannot Special Summon monsters from the Extra Deck, except \"Mayakashi\" monsters.",
    "atk": 2000,
    "def": 0,
    "level": 5,
    "race": "Zombie",
    "attribute": "DARK",
    "scale": "",
    "archetype": "Mayakashi",
    "linkval": "",
    "linkmarkers": "",
    "image_url": "https://images.ygoprodeck.com/images/cards/77714963.jpg",
    "image_url_small": "https://images.ygoprodeck.com/images/cards_small/77714963.jpg",
    "ban_tcg": "",
    "ban_ocg": "",
    "ban_goat": "",
    "staple": "",
    "views": 49906,
    "viewsweek": 0,
    "upvotes": 2,
    "downvotes": 0,
    "formats": "Duel Links|TCG|OCG|Master Duel",
    "treated_as": "",
    "tcg_date": "2018-11-15",
    "ocg_date": "2018-08-04",
    "konami_id": 14037,
    "has_effect": 1
  },
  {
    "id": 41061625,
    "name": "Yashinoki",
    "type": "Normal Monster",
    "desc": "An intelligent palm tree that drops a hail of rock-hard coconuts on its enemies.",
    "atk": 800,
    "def": 600,
    "level": 2,
    "race": "Plant",
    "attribute": "EARTH",
    "scale": "",
    "archetype": "",
    "linkval": "",
    "linkmarkers": "",
    "image_url": "https://images.ygoprodeck.com/images/cards/41061625.jpg",
    "image_url_small": "https://images.ygoprodeck.com/images/cards_small/41061625.jpg",
    "ban_tcg": "",
    "ban_ocg": "",
    "ban_goat": "",
    "staple": "",
    "views": 5290,
    "viewsweek": 0,
    "upvotes": 6,
    "downvotes": 1,
    "formats": "OCG GOAT|Duel Links|OCG|Master Duel",
    "treated_as": "",
    "tcg_date": "",
    "ocg_date": "1999-07-05",
    "konami_id": "",
    "has_effect": 0
  },
  {
    "id": 3078576,
    "name": "Yata-Garasu",
    "type": "Spirit Monster",
    "desc": "This card cannot be Special Summoned. This card returns to its owner's hand during the End Phase of the turn it is Normal Summoned or flipped face-up. When this card inflicts Battle Damage to your opponent, they skip their next Draw Phase.",
    "atk": 200,
    "def": 100,
    "level": 2,
    "race": "Fiend",
    "attribute": "WIND",
    "scale": "",
    "archetype": "",
    "linkval": "",
    "linkmarkers": "",
    "image_url": "https://images.ygoprodeck.com/images/cards/3078576.jpg",
    "image_url_small": "https://images.ygoprodeck.com/images/cards_small/3078576.jpg",
    "ban_tcg": "",
    "ban_ocg": "",
    "ban_goat": "Banned",
    "staple": "",
    "views": 150138,
    "viewsweek": 0,
    "upvotes": 27,
    "downvotes": 5,
    "formats": "GOAT|OCG GOAT|Common Charity|Edison|TCG|OCG|Master Duel",
    "treated_as": "",
    "tcg_date": "2003-06-06",
    "ocg_date": "2001-11-29",
    "konami_id": 5375,
    "has_effect": 1
  },
  {
    "id": 43202238,
    "name": "Yazi, Evil of the Yang Zing",
    "type": "Synchro Monster",
    "desc": "1 Tuner + 1 or more non-Tuner monsters\nCannot be targeted by an opponent's card effects. You can only use each of these effects of \"Yazi, Evil of the Yang Zing\" once per turn.\n● You can target 1 \"Yang Zing\" monster you control and 1 card your opponent controls; destroy them.\n● When this card you control is destroyed by battle or card effect and sent to your Graveyard: You can Special Summon 1 Wyrm-Type monster from your Deck in Defense Position.",
    "atk": 2600,
    "def": 2100,
    "level": 7,
    "race": "Wyrm",
    "attribute": "DARK",
    "scale": "",
    "archetype": "Yang Zing",
    "linkval": "",
    "linkmarkers": "",
    "image_url": "https://images.ygoprodeck.com/images/cards/43202238.jpg",
    "image_url_small": "https://images.ygoprodeck.com/images/cards_small/43202238.jpg",
    "ban_tcg": "",
    "ban_ocg": "",
    "ban_goat": "",
    "staple": "",
    "views": 383708,
    "viewsweek": 0,
    "upvotes": 9,
    "downvotes": 0,
    "formats": "Common Charity|TCG|OCG|Master Duel",
    "treated_as": "",
    "tcg_date": "2014-11-06",
    "ocg_date": "2014-07-19",
    "konami_id": 11383,
    "has_effect": 1
  },
  {
    "id": 65303664,
    "name": "Yellow Baboon, Archer of the Forest",
    "type": "Effect Monster",
    "desc": "When a Beast-Type monster you control is destroyed by battle and sent to the Graveyard, you can remove from play 2 Beast-Type monsters in your Graveyard to Special Summon this card from your hand.",
    "atk": 2600,
    "def": 1800,
    "level": 7,
    "race": "Beast",
    "attribute": "EARTH",
    "scale": "",
    "archetype": "",
    "linkval": "",
    "linkmarkers": "",
    "image_url": "https://images.ygoprodeck.com/images/cards/65303664.jpg",
    "image_url_small": "https://images.ygoprodeck.com/images/cards_small/65303664.jpg",
    "ban_tcg": "",
    "ban_ocg": "",
    "ban_goat": "",
    "staple": "",
    "views": 17557,
    "viewsweek": 0,
    "upvotes": 0,
    "downvotes": 0,
    "formats": "Duel Links|Edison|TCG|OCG|Master Duel",
    "treated_as": "",
    "tcg_date": "2009-11-17",
    "ocg_date": "2010-09-18",
    "konami_id": 8597,
    "has_effect": 1
  },
  {
    "id": 90247311,
    "name": "Yellow Dragon Ninja",
    "type": "Effect Monster",
    "desc": "Cannot be Special Summoned, except with the effect of a \"Ninja\" monster or \"Ninjitsu Art\" card. Once per turn (Quick Effect): You can send 1 \"Ninja\" monster and 1 \"Ninjitsu Art\" card from your hand and/or face-up field to the GY, then target up to 2 Spells/Traps on the field; destroy them.",
    "atk": 3000,
    "def": 1500,
    "level": 8,
    "race": "Dinosaur",
    "attribute": "WIND",
    "scale": "",
    "archetype": "Ninja",
    "linkval": "",
    "linkmarkers": "",
    "image_url": "https://images.ygoprodeck.com/images/cards/90247311.jpg",
    "image_url_small": "https://images.ygoprodeck.com/images/cards_small/90247311.jpg",
    "ban_tcg": "",
    "ban_ocg": "",
    "ban_goat": "",
    "staple": "",
    "views": 43415,
    "viewsweek": 0,
    "upvotes": 9,
    "downvotes": 1,
    "formats": "Duel Links|TCG|OCG|Master Duel",
    "treated_as": "",
    "tcg_date": "2018-08-16",
    "ocg_date": "2019-09-14",
    "konami_id": 14004,
    "has_effect": 1
  },
  {
    "id": 16366810,
    "name": "Yellow Duston",
    "type": "Effect Monster",
    "desc": "Cannot be used as a Fusion, Synchro, or Xyz Material for a Summon. While this card is face-up on the field, it cannot be Tributed. When this card on the field is destroyed: The controller targets 1 monster in their Graveyard; shuffle that target into the Deck. You can only control 1 face-up \"Yellow Duston\".",
    "atk": 0,
    "def": 1000,
    "level": 1,
    "race": "Fiend",
    "attribute": "EARTH",
    "scale": "",
    "archetype": "Duston",
    "linkval": "",
    "linkmarkers": "",
    "image_url": "https://images.ygoprodeck.com/images/cards/16366810.jpg",
    "image_url_small": "https://images.ygoprodeck.com/images/cards_small/16366810.jpg",
    "ban_tcg": "",
    "ban_ocg": "",
    "ban_goat": "",
    "staple": "",
    "views": 22625,
    "viewsweek": 0,
    "upvotes": 2,
    "downvotes": 0,
    "formats": "Duel Links|TCG|OCG|Master Duel",
    "treated_as": "",
    "tcg_date": "2013-08-08",
    "ocg_date": "2013-04-20",
    "konami_id": 10643,
    "has_effect": 1
  },
  {
    "id": 13839120,
    "name": "Yellow Gadget",
    "type": "Effect Monster",
    "desc": "When this card is Normal or Special Summoned: You can add 1 \"Green Gadget\" from your Deck to your hand.",
    "atk": 1200,
    "def": 1200,
    "level": 4,
    "race": "Machine",
    "attribute": "EARTH",
    "scale": "",
    "archetype": "Gadget",
    "linkval": "",
    "linkmarkers": "",
    "image_url": "https://images.ygoprodeck.com/images/cards/13839120.jpg",
    "image_url_small": "https://images.ygoprodeck.com/images/cards_small/13839120.jpg",
    "ban_tcg": "",
    "ban_ocg": "",
    "ban_goat": "",
    "staple": "",
    "views": 105921,
    "viewsweek": 0,
    "upvotes": 3,
    "downvotes": 0,
    "formats": "OCG GOAT|Duel Links|Common Charity|Edison|TCG|OCG|Master Duel",
    "treated_as": "",
    "tcg_date": "2007-01-17",
    "ocg_date": "2004-05-01",
    "konami_id": 6156,
    "has_effect": 1
  },
  {
    "id": 4542651,
    "name": "Yellow Luster Shield",
    "type": "Spell Card",
    "desc": "Increase the DEF of all monsters on your side of the field by 300 points.",
    "atk": "",
    "def": "",
    "level": "",
    "race": "Continuous",
    "attribute": "",
    "scale": "",
    "archetype": "",
    "linkval": "",
    "linkmarkers": "",
    "image_url": "https://images.ygoprodeck.com/images/cards/4542651.jpg",
    "image_url_small": "https://images.ygoprodeck.com/images/cards_small/4542651.jpg",
    "ban_tcg": "",
    "ban_ocg": "",
    "ban_goat": "",
    "staple": "",
    "views": 46880,
    "viewsweek": 0,
    "upvotes": 0,
    "downvotes": 2,
    "formats": "GOAT|OCG GOAT|Duel Links|Common Charity|Edison|TCG|OCG|Master Duel",
    "treated_as": "",
    "tcg_date": "2004-03-01",
    "ocg_date": "2003-04-24",
    "konami_id": 5161,
    "has_effect": 1
  },
  {
    "id": 64749612,
    "name": "Yellow Ninja",
    "type": "Effect Monster",
    "desc": "If this card is Normal Summoned or flipped face-up: You can Special Summon 1 Level 4 or lower \"Ninja\" monster from your hand in Attack Position or face-down Defense Position, also you cannot Special Summon monsters from the Extra Deck for the rest of this turn, except \"Ninja\" monsters. You can only use this effect of \"Yellow Ninja\" once per turn.",
    "atk": 1900,
    "def": 1800,
    "level": 4,
    "race": "Warrior",
    "attribute": "WIND",
    "scale": "",
    "archetype": "Ninja",
    "linkval": "",
    "linkmarkers": "",
    "image_url": "https://images.ygoprodeck.com/images/cards/64749612.jpg",
    "image_url_small": "https://images.ygoprodeck.com/images/cards_small/64749612.jpg",
    "ban_tcg": "",
    "ban_ocg": "",
    "ban_goat": "",
    "staple": "",
    "views": 57918,
    "viewsweek": 0,
    "upvotes": 4,
    "downvotes": 0,
    "formats": "Duel Links|TCG|OCG|Master Duel",
    "treated_as": "",
    "tcg_date": "2018-08-16",
    "ocg_date": "2019-09-14",
    "konami_id": 14003,
    "has_effect": 1
  },
  {
    "id": 53090623,
    "name": "Yellow-Bellied Oni",
    "type": "Effect Monster",
    "desc": "When you Xyz Summon a monster: You can Special Summon this card from your hand. Once per turn: You can detach 1 Xyz Material from a monster you control, then target 1 face-up Xyz Monster on the field; reduce its Rank by 1, and if you do, it loses 300 ATK.",
    "atk": 1000,
    "def": 1000,
    "level": 4,
    "race": "Zombie",
    "attribute": "DARK",
    "scale": "",
    "archetype": "",
    "linkval": "",
    "linkmarkers": "",
    "image_url": "https://images.ygoprodeck.com/images/cards/53090623.jpg",
    "image_url_small": "https://images.ygoprodeck.com/images/cards_small/53090623.jpg",
    "ban_tcg": "",
    "ban_ocg": "",
    "ban_goat": "",
    "staple": "",
    "views": 12480,
    "viewsweek": 0,
    "upvotes": 2,
    "downvotes": 1,
    "formats": "Duel Links|Common Charity|TCG|OCG|Master Duel",
    "treated_as": "",
    "tcg_date": "2013-11-08",
    "ocg_date": "2013-07-20",
    "konami_id": 10764,
    "has_effect": 1
  },
  {
    "id": 3486020,
    "name": "Yoko, the Graceful Mayakashi",
    "type": "Synchro Monster",
    "desc": "1 Tuner + 1+ non-Tuner monsters / You can only control 1 \"Yoko, the Graceful Mayakashi\". You can only use each of these effects of \"Yoko, the Graceful Mayakashi\" once per turn.\n● If a Synchro Monster in your possession whose original Level is 11 is destroyed by battle or an opponent's card effect while this card is in the GY: You can banish 1 other Zombie monster from your GY, and if you do, Special Summon this card.\n● If this card is Special Summoned from the GY: You can destroy 1 monster your opponent controls.",
    "atk": 2900,
    "def": 2400,
    "level": 9,
    "race": "Zombie",
    "attribute": "FIRE",
    "scale": "",
    "archetype": "Mayakashi",
    "linkval": "",
    "linkmarkers": "",
    "image_url": "https://images.ygoprodeck.com/images/cards/3486020.jpg",
    "image_url_small": "https://images.ygoprodeck.com/images/cards_small/3486020.jpg",
    "ban_tcg": "",
    "ban_ocg": "",
    "ban_goat": "",
    "staple": "",
    "views": 148986,
    "viewsweek": 0,
    "upvotes": 11,
    "downvotes": 2,
    "formats": "Duel Links|TCG|OCG|Master Duel",
    "treated_as": "",
    "tcg_date": "2018-11-15",
    "ocg_date": "2018-08-04",
    "konami_id": 14041,
    "has_effect": 1
  },
  {
    "id": 40516623,
    "name": "Yoko-Zuna Sumo Spirit",
    "type": "Pendulum Effect Monster",
    "desc": "[ Pendulum Effect ] \nIf a monster(s) is Pendulum Summoned: Return this card from the Pendulum Zone to the hand.\n[ Monster Effect ] \nWhen this card is Normal Summoned: You can send to the GY all monsters your opponent controls in the same column as the card(s) in your Pendulum Zones. Once per turn, during the End Phase, if this card was Normal Summoned or flipped face-up this turn: Return this card to the hand.",
    "atk": 2400,
    "def": 1000,
    "level": 5,
    "race": "Warrior",
    "attribute": "WIND",
    "scale": 1,
    "archetype": "Martial Art Spirit",
    "linkval": "",
    "linkmarkers": "",
    "image_url": "https://images.ygoprodeck.com/images/cards/40516623.jpg",
    "image_url_small": "https://images.ygoprodeck.com/images/cards_small/40516623.jpg",
    "ban_tcg": "",
    "ban_ocg": "",
    "ban_goat": "",
    "staple": "",
    "views": 23716,
    "viewsweek": 0,
    "upvotes": 4,
    "downvotes": 0,
    "formats": "Common Charity|TCG|OCG|Master Duel",
    "treated_as": "",
    "tcg_date": "2018-02-01",
    "ocg_date": "2018-09-08",
    "konami_id": 13532,
    "has_effect": 1
  },
  {
    "id": 27750191,
    "name": "Yokotuner",
    "type": "Tuner Monster",
    "desc": "When this card is Normal Summoned: You can Special Summon 1 Tuner from your hand or Graveyard, but it has its effects negated.",
    "atk": 800,
    "def": 600,
    "level": 1,
    "race": "Beast",
    "attribute": "EARTH",
    "scale": "",
    "archetype": "",
    "linkval": "",
    "linkmarkers": "",
    "image_url": "https://images.ygoprodeck.com/images/cards/27750191.jpg",
    "image_url_small": "https://images.ygoprodeck.com/images/cards_small/27750191.jpg",
    "ban_tcg": "",
    "ban_ocg": "",
    "ban_goat": "",
    "staple": "",
    "views": 35898,
    "viewsweek": 0,
    "upvotes": 0,
    "downvotes": 3,
    "formats": "Duel Links|Common Charity|TCG|OCG|Master Duel",
    "treated_as": "",
    "tcg_date": "2016-12-08",
    "ocg_date": "2016-10-08",
    "konami_id": 12766,
    "has_effect": 1
  },
  {
    "id": 51534754,
    "name": "Yomi Ship",
    "type": "Effect Monster",
    "desc": "If this card is destroyed by battle and sent to the GY: Destroy the monster that destroyed this card.",
    "atk": 800,
    "def": 1400,
    "level": 3,
    "race": "Aqua",
    "attribute": "WATER",
    "scale": "",
    "archetype": "",
    "linkval": "",
    "linkmarkers": "",
    "image_url": "https://images.ygoprodeck.com/images/cards/51534754.jpg",
    "image_url_small": "https://images.ygoprodeck.com/images/cards_small/51534754.jpg",
    "ban_tcg": "",
    "ban_ocg": "",
    "ban_goat": "",
    "staple": "",
    "views": 137643,
    "viewsweek": 26,
    "upvotes": 5,
    "downvotes": 3,
    "formats": "GOAT|OCG GOAT|Speed Duel|Duel Links|Common Charity|Edison|TCG|OCG|Master Duel",
    "treated_as": "",
    "tcg_date": "2003-07-18",
    "ocg_date": "2002-05-16",
    "konami_id": 5521,
    "has_effect": 1
  },
  {
    "id": 57511992,
    "name": "Yorishiro of the Aqua",
    "type": "Effect Monster",
    "desc": "You can target 1 WATER monster in your GY; apply 1 of these effects, also you cannot Special Summon monsters for the rest of this turn, except WATER monsters.\n● (Only if the target has a Level) until the End Phase, this card's Level, also its name, become the same as that monster's.\n● (Only if \"Umi\" is on the field), Special Summon that monster in Defense Position.\nYou can banish this card from your GY, then target 1 \"Umi\" in your GY; add it to your hand. You can only use each effect of \"Yorishiro of the Aqua\" once per turn.",
    "atk": 700,
    "def": 2000,
    "level": 4,
    "race": "Aqua",
    "attribute": "WATER",
    "scale": "",
    "archetype": "",
    "linkval": "",
    "linkmarkers": "",
    "image_url": "https://images.ygoprodeck.com/images/cards/57511992.jpg",
    "image_url_small": "https://images.ygoprodeck.com/images/cards_small/57511992.jpg",
    "ban_tcg": "",
    "ban_ocg": "",
    "ban_goat": "",
    "staple": "",
    "views": 17099,
    "viewsweek": 0,
    "upvotes": 2,
    "downvotes": 0,
    "formats": "Common Charity|TCG|OCG|Master Duel",
    "treated_as": "",
    "tcg_date": "2022-10-20",
    "ocg_date": "2021-11-20",
    "konami_id": 17103,
    "has_effect": 1
  },
  {
    "id": 17115745,
    "name": "Yormungarde",
    "type": "Normal Monster",
    "desc": "An extremely long snake that dwells in the world of myth.",
    "atk": 1200,
    "def": 900,
    "level": 3,
    "race": "Reptile",
    "attribute": "EARTH",
    "scale": "",
    "archetype": "",
    "linkval": "",
    "linkmarkers": "",
    "image_url": "https://images.ygoprodeck.com/images/cards/17115745.jpg",
    "image_url_small": "https://images.ygoprodeck.com/images/cards_small/17115745.jpg",
    "ban_tcg": "",
    "ban_ocg": "",
    "ban_goat": "",
    "staple": "",
    "views": 7339,
    "viewsweek": 0,
    "upvotes": 10,
    "downvotes": 0,
    "formats": "OCG GOAT|Duel Links|OCG|Master Duel",
    "treated_as": "",
    "tcg_date": "",
    "ocg_date": "1999-07-05",
    "konami_id": "",
    "has_effect": 0
  },
  {
    "id": 27918963,
    "name": "Yosen Training Grounds",
    "type": "Spell Card",
    "desc": "Each time a \"Yosenju\" monster(s) is Normal or Special Summoned, place 1 Yosen Counter on this card. You can remove any number of Yosen Counters from this card; apply this effect, depending on the number of Yosen Counters removed. You can only use this effect of \"Yosen Training Grounds\" once per turn.\n● 1 Counter: All \"Yosenju\" monsters you currently control gain 300 ATK until the end of this turn (even if this card leaves the field).\n● 3 Counters: Add 1 \"Yosenju\" card from your Deck or Graveyard to your hand.",
    "atk": "",
    "def": "",
    "level": "",
    "race": "Continuous",
    "attribute": "",
    "scale": "",
    "archetype": "Yosenju",
    "linkval": "",
    "linkmarkers": "",
    "image_url": "https://images.ygoprodeck.com/images/cards/27918963.jpg",
    "image_url_small": "https://images.ygoprodeck.com/images/cards_small/27918963.jpg",
    "ban_tcg": "",
    "ban_ocg": "",
    "ban_goat": "",
    "staple": "",
    "views": 25958,
    "viewsweek": 0,
    "upvotes": 4,
    "downvotes": 3,
    "formats": "Duel Links|TCG|OCG|Master Duel",
    "treated_as": "",
    "tcg_date": "2015-02-12",
    "ocg_date": "2014-10-11",
    "konami_id": 11478,
    "has_effect": 1
  },
  {
    "id": 79861914,
    "name": "Yosen Whirlwind",
    "type": "Spell Card",
    "desc": "Activate this card by paying 800 LP. Once per turn, if a face-up \"Yosenju\" monster you control returns to the hand (except during the Damage Step): You can target 1 card your opponent controls; return it to the hand. During your End Phase, unless this effect was activated this turn (and was not negated), destroy this card.",
    "atk": "",
    "def": "",
    "level": "",
    "race": "Continuous",
    "attribute": "",
    "scale": "",
    "archetype": "Yosenju",
    "linkval": "",
    "linkmarkers": "",
    "image_url": "https://images.ygoprodeck.com/images/cards/79861914.jpg",
    "image_url_small": "https://images.ygoprodeck.com/images/cards_small/79861914.jpg",
    "ban_tcg": "",
    "ban_ocg": "",
    "ban_goat": "",
    "staple": "",
    "views": 16468,
    "viewsweek": 0,
    "upvotes": 4,
    "downvotes": 3,
    "formats": "Duel Links|Common Charity|TCG|OCG|Master Duel",
    "treated_as": "",
    "tcg_date": "2015-05-14",
    "ocg_date": "2015-02-14",
    "konami_id": 11733,
    "has_effect": 1
  },
  {
    "id": 85970321,
    "name": "Yosenju Izna",
    "type": "Effect Monster",
    "desc": "Once per turn, during the End Phase, if this card was Normal Summoned this turn: Return it to the hand. You can only use each of the following effects of \"Yosenju Izna\" once per turn.\n● You can discard this card; this turn, your opponent cannot activate cards or effects when a \"Yosenju\" monster(s) is Normal or Special Summoned.\n● If you control another \"Yosenju\" monster: You can draw 1 card.",
    "atk": 800,
    "def": 1200,
    "level": 4,
    "race": "Beast-Warrior",
    "attribute": "WIND",
    "scale": "",
    "archetype": "Yosenju",
    "linkval": "",
    "linkmarkers": "",
    "image_url": "https://images.ygoprodeck.com/images/cards/85970321.jpg",
    "image_url_small": "https://images.ygoprodeck.com/images/cards_small/85970321.jpg",
    "ban_tcg": "",
    "ban_ocg": "",
    "ban_goat": "",
    "staple": "",
    "views": 38705,
    "viewsweek": 0,
    "upvotes": 4,
    "downvotes": 4,
    "formats": "Duel Links|Common Charity|TCG|OCG|Master Duel",
    "treated_as": "",
    "tcg_date": "2019-07-25",
    "ocg_date": "2019-04-13",
    "konami_id": 14468,
    "has_effect": 1
  },
  {
    "id": 65247798,
    "name": "Yosenju Kama 1",
    "type": "Effect Monster",
    "desc": "If this card is Normal Summoned, you can: Immediately after this effect resolves, Normal Summon 1 \"Yosenju\" monster from your hand, except \"Yosenju Kama 1\". If you control another \"Yosenju\" monster: You can target 1 face-up card your opponent controls; return it to the hand. This effect can only be used once while this card is face-up on the field. Once per turn, during the End Phase, if this card was Normal Summoned this turn: Return it to the hand.",
    "atk": 1600,
    "def": 500,
    "level": 4,
    "race": "Beast-Warrior",
    "attribute": "WIND",
    "scale": "",
    "archetype": "Yosenju",
    "linkval": "",
    "linkmarkers": "",
    "image_url": "https://images.ygoprodeck.com/images/cards/65247798.jpg",
    "image_url_small": "https://images.ygoprodeck.com/images/cards_small/65247798.jpg",
    "ban_tcg": "",
    "ban_ocg": "",
    "ban_goat": "",
    "staple": "",
    "views": 64582,
    "viewsweek": 0,
    "upvotes": 6,
    "downvotes": 1,
    "formats": "Duel Links|Common Charity|TCG|OCG|Master Duel",
    "treated_as": "",
    "tcg_date": "2015-02-12",
    "ocg_date": "2014-10-11",
    "konami_id": 11473,
    "has_effect": 1
  },
  {
    "id": 92246806,
    "name": "Yosenju Kama 2",
    "type": "Effect Monster",
    "desc": "If this card is Normal Summoned, you can: Immediately after this effect resolves, Normal Summon 1 \"Yosenju\" monster from your hand, except \"Yosenju Kama 2\". This card can attack your opponent directly, but when it does so using this effect, the battle damage inflicted to your opponent is halved. Once per turn, during the End Phase, if this card was Normal Summoned this turn: Return it to the hand.",
    "atk": 1800,
    "def": 200,
    "level": 4,
    "race": "Beast-Warrior",
    "attribute": "WIND",
    "scale": "",
    "archetype": "Yosenju",
    "linkval": "",
    "linkmarkers": "",
    "image_url": "https://images.ygoprodeck.com/images/cards/92246806.jpg",
    "image_url_small": "https://images.ygoprodeck.com/images/cards_small/92246806.jpg",
    "ban_tcg": "",
    "ban_ocg": "",
    "ban_goat": "",
    "staple": "",
    "views": 59454,
    "viewsweek": 26,
    "upvotes": 4,
    "downvotes": 1,
    "formats": "Duel Links|Common Charity|TCG|OCG|Master Duel",
    "treated_as": "",
    "tcg_date": "2015-02-12",
    "ocg_date": "2014-10-11",
    "konami_id": 11474,
    "has_effect": 1
  },
  {
    "id": 28630501,
    "name": "Yosenju Kama 3",
    "type": "Effect Monster",
    "desc": "If this card is Normal Summoned, you can: Immediately after this effect resolves, Normal Summon 1 \"Yosenju\" monster from your hand, except \"Yosenju Kama 3\". When another \"Yosenju\" monster you control inflicts battle damage to your opponent: You can add 1 \"Yosenju\" card from your Deck to your hand, except \"Yosenju Kama 3\". You can only use this effect of \"Yosenju Kama 3\" once per turn. Once per turn, during the End Phase, if this card was Normal Summoned this turn: Return it to the hand.",
    "atk": 1500,
    "def": 800,
    "level": 4,
    "race": "Beast-Warrior",
    "attribute": "WIND",
    "scale": "",
    "archetype": "Yosenju",
    "linkval": "",
    "linkmarkers": "",
    "image_url": "https://images.ygoprodeck.com/images/cards/28630501.jpg",
    "image_url_small": "https://images.ygoprodeck.com/images/cards_small/28630501.jpg",
    "ban_tcg": "",
    "ban_ocg": "",
    "ban_goat": "",
    "staple": "",
    "views": 56107,
    "viewsweek": 0,
    "upvotes": 3,
    "downvotes": 3,
    "formats": "Duel Links|Common Charity|TCG|OCG|Master Duel",
    "treated_as": "",
    "tcg_date": "2015-02-12",
    "ocg_date": "2014-10-11",
    "konami_id": 11475,
    "has_effect": 1
  },
  {
    "id": 23740893,
    "name": "Yosenju Kodam",
    "type": "Effect Monster",
    "desc": "You can Tribute this card, then target 1 \"Yosen Training Grounds\" you control; place 3 Yosen Counters on it. You can only use this effect of \"Yosenju Kodam\" once per turn. You can banish this card from your Graveyard; you can Normal Summon 1 \"Yosenju\" monster during your Main Phase this turn, in addition to your Normal Summon/Set. (You can only gain this effect once per turn.)",
    "atk": 0,
    "def": 0,
    "level": 1,
    "race": "Beast-Warrior",
    "attribute": "WIND",
    "scale": "",
    "archetype": "Yosenju",
    "linkval": "",
    "linkmarkers": "",
    "image_url": "https://images.ygoprodeck.com/images/cards/23740893.jpg",
    "image_url_small": "https://images.ygoprodeck.com/images/cards_small/23740893.jpg",
    "ban_tcg": "",
    "ban_ocg": "",
    "ban_goat": "",
    "staple": "",
    "views": 13927,
    "viewsweek": 0,
    "upvotes": 3,
    "downvotes": 0,
    "formats": "Duel Links|Common Charity|TCG|OCG|Master Duel",
    "treated_as": "",
    "tcg_date": "2015-05-14",
    "ocg_date": "2015-02-14",
    "konami_id": 11693,
    "has_effect": 1
  },
  {
    "id": 49249907,
    "name": "Yosenju Magat",
    "type": "Effect Monster",
    "desc": "If this card is Normal Summoned: You can Special Summon 1 \"Yosenju\" monster from your Deck, except \"Yosenju Magat\". During the End Phase, if this card was Special Summoned this turn: Return it to the hand.",
    "atk": 2000,
    "def": 100,
    "level": 6,
    "race": "Beast",
    "attribute": "WIND",
    "scale": "",
    "archetype": "Yosenju",
    "linkval": "",
    "linkmarkers": "",
    "image_url": "https://images.ygoprodeck.com/images/cards/49249907.jpg",
    "image_url_small": "https://images.ygoprodeck.com/images/cards_small/49249907.jpg",
    "ban_tcg": "",
    "ban_ocg": "",
    "ban_goat": "",
    "staple": "",
    "views": 18016,
    "viewsweek": 0,
    "upvotes": 2,
    "downvotes": 3,
    "formats": "Duel Links|Common Charity|TCG|OCG|Master Duel",
    "treated_as": "",
    "tcg_date": "2015-01-15",
    "ocg_date": "2014-11-15",
    "konami_id": 11546,
    "has_effect": 1
  },
  {
    "id": 39853199,
    "name": "Yosenju Misak",
    "type": "Effect Monster",
    "desc": "At the start of the Damage Step, if this card battles a face-up non-WIND monster: You can destroy that monster. When this card is Pendulum Summoned: You can target 1 card your opponent controls; destroy it. During the End Phase, if this card was Special Summoned this turn: Return it to the hand.",
    "atk": 2300,
    "def": 200,
    "level": 6,
    "race": "Beast",
    "attribute": "WIND",
    "scale": "",
    "archetype": "Yosenju",
    "linkval": "",
    "linkmarkers": "",
    "image_url": "https://images.ygoprodeck.com/images/cards/39853199.jpg",
    "image_url_small": "https://images.ygoprodeck.com/images/cards_small/39853199.jpg",
    "ban_tcg": "",
    "ban_ocg": "",
    "ban_goat": "",
    "staple": "",
    "views": 19359,
    "viewsweek": 0,
    "upvotes": 1,
    "downvotes": 1,
    "formats": "TCG|OCG|Master Duel",
    "treated_as": "",
    "tcg_date": "2015-02-12",
    "ocg_date": "2014-10-11",
    "konami_id": 11472,
    "has_effect": 1
  },
  {
    "id": 61884774,
    "name": "Yosenju Oroshi Channeling",
    "type": "Spell Card",
    "desc": "If you control no monsters: Activate 1 of the following effects; also for the rest of this turn after this card resolves, you cannot Special Summon monsters, except \"Yosenju\" monsters.\n● Add 1 Level 5 or higher \"Yosenju\" monster from your Deck to your hand.\n● Place 1 \"Yosenju Shinchu L\" and 1 \"Yosenju Shinchu R\" from your Deck in your Pendulum Zones, but destroy them during your opponent's next End Phase.",
    "atk": "",
    "def": "",
    "level": "",
    "race": "Normal",
    "attribute": "",
    "scale": "",
    "archetype": "Yosenju",
    "linkval": "",
    "linkmarkers": "",
    "image_url": "https://images.ygoprodeck.com/images/cards/61884774.jpg",
    "image_url_small": "https://images.ygoprodeck.com/images/cards_small/61884774.jpg",
    "ban_tcg": "",
    "ban_ocg": "",
    "ban_goat": "",
    "staple": "",
    "views": 35920,
    "viewsweek": 0,
    "upvotes": 4,
    "downvotes": 1,
    "formats": "Common Charity|TCG|OCG|Master Duel",
    "treated_as": "",
    "tcg_date": "2019-07-25",
    "ocg_date": "2016-11-26",
    "konami_id": 12864,
    "has_effect": 1
  },
  {
    "id": 69838592,
    "name": "Yosenju Oyam",
    "type": "Effect Monster",
    "desc": "When an opponent's monster declares a direct attack: You can send 1 \"Yosenju\" monster from your hand to the Graveyard, except \"Yosenju Oyam\"; Special Summon this card from your hand. You can only use this effect of \"Yosenju Oyam\" once per turn. At the start of the Damage Step, if this card battles an opponent's face-up monster: You can make this card's ATK and DEF become equal to the original ATK of the opponent's monster it is battling, until the end of this turn. When this card is destroyed by battle and sent to the Graveyard: You can add 1 \"Yosenju\" card from your Deck to your hand.",
    "atk": 0,
    "def": 0,
    "level": 6,
    "race": "Beast",
    "attribute": "WIND",
    "scale": "",
    "archetype": "Yosenju",
    "linkval": "",
    "linkmarkers": "",
    "image_url": "https://images.ygoprodeck.com/images/cards/69838592.jpg",
    "image_url_small": "https://images.ygoprodeck.com/images/cards_small/69838592.jpg",
    "ban_tcg": "",
    "ban_ocg": "",
    "ban_goat": "",
    "staple": "",
    "views": 23298,
    "viewsweek": 0,
    "upvotes": 1,
    "downvotes": 1,
    "formats": "Duel Links|TCG|OCG|Master Duel",
    "treated_as": "",
    "tcg_date": "2015-05-14",
    "ocg_date": "2015-02-14",
    "konami_id": 11694,
    "has_effect": 1
  },
  {
    "id": 58981727,
    "name": "Yosenju Sabu",
    "type": "Effect Monster",
    "desc": "Once per turn, during the End Phase, if this card was Normal Summoned this turn: Return it to the hand. You can only use each of the following effects of \"Yosenju Sabu\" once per turn.\n● If this card is Normal Summoned: If you control another \"Yosenju\" card, you can add 1 \"Yosenju\" Pendulum Monster from your Deck to your hand.\n● You can target 1 \"Yosenju\" card you control; place 1 \"Dizzying Winds of Yosen Village\" or \"Yosen Whirlwind\" from your Deck face-up in your Spell & Trap Zone, and if you do, shuffle the targeted card into the Deck.",
    "atk": 1700,
    "def": 400,
    "level": 4,
    "race": "Beast-Warrior",
    "attribute": "WIND",
    "scale": "",
    "archetype": "Yosenju",
    "linkval": "",
    "linkmarkers": "",
    "image_url": "https://images.ygoprodeck.com/images/cards/58981727.jpg",
    "image_url_small": "https://images.ygoprodeck.com/images/cards_small/58981727.jpg",
    "ban_tcg": "",
    "ban_ocg": "",
    "ban_goat": "",
    "staple": "",
    "views": 38636,
    "viewsweek": 0,
    "upvotes": 3,
    "downvotes": 3,
    "formats": "Common Charity|TCG|OCG|Master Duel",
    "treated_as": "",
    "tcg_date": "2019-07-25",
    "ocg_date": "2019-04-13",
    "konami_id": 14467,
    "has_effect": 1
  },
  {
    "id": 65025250,
    "name": "Yosenju Shinchu L",
    "type": "Pendulum Effect Monster",
    "desc": "[ Pendulum Effect ] \nIf a \"Yosenju\" monster(s) you control would be destroyed by battle or card effect, you can destroy this card instead.\n[ Monster Effect ] \nIf this card is Normal Summoned: Change it to Defense Position. Your opponent cannot target \"Yosenju\" monsters you control with card effects, except this one.",
    "atk": 0,
    "def": 2100,
    "level": 4,
    "race": "Rock",
    "attribute": "WIND",
    "scale": 3,
    "archetype": "Yosenju",
    "linkval": "",
    "linkmarkers": "",
    "image_url": "https://images.ygoprodeck.com/images/cards/65025250.jpg",
    "image_url_small": "https://images.ygoprodeck.com/images/cards_small/65025250.jpg",
    "ban_tcg": "",
    "ban_ocg": "",
    "ban_goat": "",
    "staple": "",
    "views": 37045,
    "viewsweek": 0,
    "upvotes": 4,
    "downvotes": 1,
    "formats": "Duel Links|Common Charity|TCG|OCG|Master Duel",
    "treated_as": "",
    "tcg_date": "2015-02-12",
    "ocg_date": "2014-10-11",
    "konami_id": 11476,
    "has_effect": 1
  },
  {
    "id": 91420254,
    "name": "Yosenju Shinchu R",
    "type": "Pendulum Effect Monster",
    "desc": "[ Pendulum Effect ] \nOnce per turn, if you have a \"Yosenju\" card in your other Pendulum Zone: You can make this card's Pendulum Scale become 11 until the end of this turn, also you cannot Special Summon monsters for the rest of this turn, except \"Yosenju\" monsters (even if this card leaves the field).\n[ Monster Effect ] \nIf this card is Normal Summoned: Change it to Defense Position. Monsters your opponent controls cannot target face-up \"Yosenju\" monsters for attacks, except this one.",
    "atk": 0,
    "def": 2100,
    "level": 4,
    "race": "Rock",
    "attribute": "WIND",
    "scale": 5,
    "archetype": "Yosenju",
    "linkval": "",
    "linkmarkers": "",
    "image_url": "https://images.ygoprodeck.com/images/cards/91420254.jpg",
    "image_url_small": "https://images.ygoprodeck.com/images/cards_small/91420254.jpg",
    "ban_tcg": "",
    "ban_ocg": "",
    "ban_goat": "",
    "staple": "",
    "views": 30951,
    "viewsweek": 0,
    "upvotes": 4,
    "downvotes": 2,
    "formats": "Duel Links|Common Charity|TCG|OCG|Master Duel",
    "treated_as": "",
    "tcg_date": "2015-02-12",
    "ocg_date": "2014-10-11",
    "konami_id": 11477,
    "has_effect": 1
  },
  {
    "id": 25244515,
    "name": "Yosenju Tsujik",
    "type": "Effect Monster",
    "desc": "During the End Phase, if this card was Normal Summoned this turn: Return it to the hand. You can only use each of these effects of \"Yosenju Tsujik\" once per turn.\n● During either player's Damage Step, when a \"Yosenju\" monster you control battles an opponent's monster: You can discard this card; that monster you control gains 1000 ATK until the end of this turn.\n● You can target 1 \"Yosenju\" monster on the field; it gains 1000 ATK until the end of this turn.",
    "atk": 1000,
    "def": 0,
    "level": 4,
    "race": "Beast-Warrior",
    "attribute": "WIND",
    "scale": "",
    "archetype": "Yosenju",
    "linkval": "",
    "linkmarkers": "",
    "image_url": "https://images.ygoprodeck.com/images/cards/25244515.jpg",
    "image_url_small": "https://images.ygoprodeck.com/images/cards_small/25244515.jpg",
    "ban_tcg": "",
    "ban_ocg": "",
    "ban_goat": "",
    "staple": "",
    "views": 34222,
    "viewsweek": 0,
    "upvotes": 3,
    "downvotes": 2,
    "formats": "Duel Links|Common Charity|TCG|OCG|Master Duel",
    "treated_as": "",
    "tcg_date": "2015-01-15",
    "ocg_date": "2014-11-15",
    "konami_id": 11547,
    "has_effect": 1
  },
  {
    "id": 54880296,
    "name": "Yosenju Wind Worship",
    "type": "Spell Card",
    "desc": "If you control 3 or more \"Yosenju\" Monster Cards with different names: Return as many \"Yosenju\" Monster Cards you control to the hand as possible, then you can draw until you have 5 cards in your hand. You can only activate 1 \"Yosenju Wind Worship\" per turn.",
    "atk": "",
    "def": "",
    "level": "",
    "race": "Quick-Play",
    "attribute": "",
    "scale": "",
    "archetype": "Yosenju",
    "linkval": "",
    "linkmarkers": "",
    "image_url": "https://images.ygoprodeck.com/images/cards/54880296.jpg",
    "image_url_small": "https://images.ygoprodeck.com/images/cards_small/54880296.jpg",
    "ban_tcg": "",
    "ban_ocg": "",
    "ban_goat": "",
    "staple": "",
    "views": 15596,
    "viewsweek": 0,
    "upvotes": 3,
    "downvotes": 2,
    "formats": "Duel Links|Common Charity|TCG|OCG|Master Duel",
    "treated_as": "",
    "tcg_date": "2019-07-25",
    "ocg_date": "2019-04-13",
    "konami_id": 14510,
    "has_effect": 1
  },
  {
    "id": 54903668,
    "name": "Yosenjus' Secret Move",
    "type": "Trap Card",
    "desc": "When a Spell/Trap Card, or monster effect, is activated while you control at least 1 \"Yosenju\" card, and all face-up monsters you control are \"Yosenju\" monsters: Negate the activation, and if you do, destroy that card.",
    "atk": "",
    "def": "",
    "level": "",
    "race": "Counter",
    "attribute": "",
    "scale": "",
    "archetype": "Yosenju",
    "linkval": "",
    "linkmarkers": "",
    "image_url": "https://images.ygoprodeck.com/images/cards/54903668.jpg",
    "image_url_small": "https://images.ygoprodeck.com/images/cards_small/54903668.jpg",
    "ban_tcg": "",
    "ban_ocg": "",
    "ban_goat": "",
    "staple": "",
    "views": 26391,
    "viewsweek": 0,
    "upvotes": 4,
    "downvotes": 3,
    "formats": "Duel Links|Common Charity|TCG|OCG|Master Duel",
    "treated_as": "",
    "tcg_date": "2015-02-12",
    "ocg_date": "2014-10-11",
    "konami_id": 11479,
    "has_effect": 1
  },
  {
    "id": 10612222,
    "name": "Yosenjus' Sword Sting",
    "type": "Trap Card",
    "desc": "If you control no monsters: Reveal up to 2 \"Yosenju\" monsters with different names in your hand, then target the same number of face-up cards your opponent controls; return them to the hand. You can only activate 1 \"Yosenjus' Sword Sting\" per turn.",
    "atk": "",
    "def": "",
    "level": "",
    "race": "Normal",
    "attribute": "",
    "scale": "",
    "archetype": "Yosenju",
    "linkval": "",
    "linkmarkers": "",
    "image_url": "https://images.ygoprodeck.com/images/cards/10612222.jpg",
    "image_url_small": "https://images.ygoprodeck.com/images/cards_small/10612222.jpg",
    "ban_tcg": "",
    "ban_ocg": "",
    "ban_goat": "",
    "staple": "",
    "views": 42657,
    "viewsweek": 0,
    "upvotes": 3,
    "downvotes": 1,
    "formats": "Duel Links|Common Charity|TCG|OCG|Master Duel",
    "treated_as": "",
    "tcg_date": "2019-07-25",
    "ocg_date": "2019-04-13",
    "konami_id": 14521,
    "has_effect": 1
  },
  {
    "id": 32056070,
    "name": "You and A.I.",
    "type": "Spell Card",
    "desc": "If a Cyberse monster(s) with 2300 original ATK is Special Summoned: You can activate 1 of these effects, based on the Attribute of that monster(s) on the field;\n● EARTH/WATER: Halve the ATK of 1 face-up monster on the field until the end of this turn.\n● WIND/LIGHT: Negate the effects of 1 face-up card on the field until the end of this turn.\n● FIRE/DARK: Special Summon 1 \"@Ignister Token\" (Cyberse/DARK/Level 1/ATK 0/DEF 0).\nYou can only use each effect of \"You and A.I.\" once per turn for each Attribute.",
    "atk": "",
    "def": "",
    "level": "",
    "race": "Continuous",
    "attribute": "",
    "scale": "",
    "archetype": "A.I.",
    "linkval": "",
    "linkmarkers": "",
    "image_url": "https://images.ygoprodeck.com/images/cards/32056070.jpg",
    "image_url_small": "https://images.ygoprodeck.com/images/cards_small/32056070.jpg",
    "ban_tcg": "",
    "ban_ocg": "",
    "ban_goat": "",
    "staple": "",
    "views": 22609,
    "viewsweek": 0,
    "upvotes": 1,
    "downvotes": 1,
    "formats": "Common Charity|TCG|OCG|Master Duel",
    "treated_as": "",
    "tcg_date": "2021-06-03",
    "ocg_date": "2021-01-16",
    "konami_id": 16022,
    "has_effect": 1
  },
  {
    "id": 88346805,
    "name": "You're Finished",
    "type": "Trap Card",
    "desc": "If 10 or more cards and/or effects have been activated during this turn: Special Summon this card as an Effect Monster (Cyberse/DARK/Level 10/ATK 3000/DEF 3000) (this card is also still a Trap), but Set it in your Spell & Trap Zone during your End Phase. Once per turn, when your opponent activates a card or effect, while this card is in your Monster Zone (Quick Effect): You can destroy as many cards your opponent controls as possible, then Set this card in your Spell & Trap Zone.",
    "atk": "",
    "def": "",
    "level": "",
    "race": "Continuous",
    "attribute": "",
    "scale": "",
    "archetype": "",
    "linkval": "",
    "linkmarkers": "",
    "image_url": "https://images.ygoprodeck.com/images/cards/88346805.jpg",
    "image_url_small": "https://images.ygoprodeck.com/images/cards_small/88346805.jpg",
    "ban_tcg": "",
    "ban_ocg": "",
    "ban_goat": "",
    "staple": "",
    "views": 10607,
    "viewsweek": 0,
    "upvotes": 0,
    "downvotes": 0,
    "formats": "TCG|OCG",
    "treated_as": "",
    "tcg_date": "2023-07-27",
    "ocg_date": "2023-04-22",
    "konami_id": 18867,
    "has_effect": 1
  },
  {
    "id": 10312660,
    "name": "You're in Danger!",
    "type": "Trap Card",
    "desc": "Reveal 3 \"Danger!\" monsters with different names from your Deck, your opponent randomly picks 1 for you to Special Summon, and you shuffle the rest into the Deck. During the End Phase, destroy that Special Summoned monster. You can only activate 1 \"You're in Danger!\" per turn.",
    "atk": "",
    "def": "",
    "level": "",
    "race": "Normal",
    "attribute": "",
    "scale": "",
    "archetype": "Danger!",
    "linkval": "",
    "linkmarkers": "",
    "image_url": "https://images.ygoprodeck.com/images/cards/10312660.jpg",
    "image_url_small": "https://images.ygoprodeck.com/images/cards_small/10312660.jpg",
    "ban_tcg": "",
    "ban_ocg": "",
    "ban_goat": "",
    "staple": "",
    "views": 23103,
    "viewsweek": 0,
    "upvotes": 4,
    "downvotes": 0,
    "formats": "Common Charity|TCG|OCG|Master Duel",
    "treated_as": "",
    "tcg_date": "2019-05-02",
    "ocg_date": "2019-02-12",
    "konami_id": 14535,
    "has_effect": 1
  },
  {
    "id": 33393090,
    "name": "Yowie",
    "type": "Effect Monster",
    "desc": "If this card is Summoned (and no other cards): You can activate this effect; your opponent skips their next Draw Phase. You can only Special Summon once, the turn you activate this effect. You can only use this effect of \"Yowie\" once per Duel.",
    "atk": 500,
    "def": 500,
    "level": 3,
    "race": "Reptile",
    "attribute": "EARTH",
    "scale": "",
    "archetype": "",
    "linkval": "",
    "linkmarkers": "",
    "image_url": "https://images.ygoprodeck.com/images/cards/33393090.jpg",
    "image_url_small": "https://images.ygoprodeck.com/images/cards_small/33393090.jpg",
    "ban_tcg": "",
    "ban_ocg": "",
    "ban_goat": "",
    "staple": "",
    "views": 7859,
    "viewsweek": 0,
    "upvotes": 1,
    "downvotes": 0,
    "formats": "TCG|OCG|Master Duel",
    "treated_as": "",
    "tcg_date": "2021-06-03",
    "ocg_date": "2021-06-12",
    "konami_id": 16403,
    "has_effect": 1
  },
  {
    "id": 81332143,
    "name": "Yu-Jo Friendship",
    "type": "Spell Card",
    "desc": "Offer your opponent a handshake. If they accept your handshake, each player's Life Points become half the combined Life Points of both players. If you have \"Unity\" in your hand and show it to your opponent, they must accept the handshake.",
    "atk": "",
    "def": "",
    "level": "",
    "race": "Normal",
    "attribute": "",
    "scale": "",
    "archetype": "",
    "linkval": "",
    "linkmarkers": "",
    "image_url": "https://images.ygoprodeck.com/images/cards/81332143.jpg",
    "image_url_small": "https://images.ygoprodeck.com/images/cards_small/81332143.jpg",
    "ban_tcg": "",
    "ban_ocg": "",
    "ban_goat": "",
    "staple": "",
    "views": 26002,
    "viewsweek": 0,
    "upvotes": 8,
    "downvotes": 4,
    "formats": "OCG GOAT|Duel Links|Edison|TCG|OCG|Master Duel",
    "treated_as": "",
    "tcg_date": "2006-05-01",
    "ocg_date": "2002-11-01",
    "konami_id": 5754,
    "has_effect": 1
  },
  {
    "id": 78371393,
    "name": "Yubel",
    "type": "Effect Monster",
    "desc": "This card cannot be destroyed by battle. You take no Battle Damage from battles involving this card. Before damage calculation, when this face-up Attack Position card is attacked by an opponent's monster: Inflict damage to your opponent equal to that monster's ATK. During your End Phase: Tribute 1 other monster or destroy this card. When this card is destroyed, except by its own effect: Its owner can Special Summon 1 \"Yubel - Terror Incarnate\" from their hand, Deck, or Graveyard.",
    "atk": 0,
    "def": 0,
    "level": 10,
    "race": "Fiend",
    "attribute": "DARK",
    "scale": "",
    "archetype": "Yubel",
    "linkval": "",
    "linkmarkers": "",
    "image_url": "https://images.ygoprodeck.com/images/cards/78371393.jpg",
    "image_url_small": "https://images.ygoprodeck.com/images/cards_small/78371393.jpg",
    "ban_tcg": "",
    "ban_ocg": "",
    "ban_goat": "",
    "staple": "",
    "views": 359700,
    "viewsweek": 0,
    "upvotes": 38,
    "downvotes": 9,
    "formats": "Duel Links|Edison|TCG|OCG|Master Duel",
    "treated_as": "",
    "tcg_date": "2008-01-26",
    "ocg_date": "2007-11-23",
    "konami_id": 7409,
    "has_effect": 1
  },
  {
    "id": 4779091,
    "name": "Yubel - Terror Incarnate",
    "type": "Effect Monster",
    "desc": "Cannot be Normal Summoned or Set. Must be Special Summoned by \"Yubel\", and cannot be Special Summoned by other ways. This card cannot be destroyed by battle. You take no Battle Damage from battles involving this card. Before damage calculation, when this face-up Attack Position card is attacked by an opponent's monster: Inflict damage to your opponent equal to that monster's ATK. During your End Phase: Destroy all other monsters on the field. When this face-up card leaves the field: You can Special Summon 1 \"Yubel - The Ultimate Nightmare\" from your hand, Deck, or Graveyard.",
    "atk": 0,
    "def": 0,
    "level": 11,
    "race": "Fiend",
    "attribute": "DARK",
    "scale": "",
    "archetype": "Yubel",
    "linkval": "",
    "linkmarkers": "",
    "image_url": "https://images.ygoprodeck.com/images/cards/4779091.jpg",
    "image_url_small": "https://images.ygoprodeck.com/images/cards_small/4779091.jpg",
    "ban_tcg": "",
    "ban_ocg": "",
    "ban_goat": "",
    "staple": "",
    "views": 229180,
    "viewsweek": 26,
    "upvotes": 6,
    "downvotes": 1,
    "formats": "Duel Links|Edison|TCG|OCG|Master Duel",
    "treated_as": "",
    "tcg_date": "2008-01-26",
    "ocg_date": "2007-11-23",
    "konami_id": 7410,
    "has_effect": 1
  },
  {
    "id": 47172959,
    "name": "Yubel - The Loving Defender Forever",
    "type": "Fusion Monster",
    "desc": "1 \"Yubel\" monster + 1+ Effect Monsters on the field\nIf this card is Fusion Summoned: You can inflict 500 damage to your opponent for each material used. You can only use this effect of \"Yubel - The Loving Defender Forever\" once per turn. Cannot be destroyed by battle or card effects, also you take no battle damage from battles involving this card. At the end of the Damage Step, if this card battled an opponent's monster: Inflict damage to your opponent equal to that opponent's monster's ATK, and if you do, banish that monster.",
    "atk": 0,
    "def": 0,
    "level": 12,
    "race": "Fiend",
    "attribute": "DARK",
    "scale": "",
    "archetype": "Yubel",
    "linkval": "",
    "linkmarkers": "",
    "image_url": "https://images.ygoprodeck.com/images/cards/47172959.jpg",
    "image_url_small": "https://images.ygoprodeck.com/images/cards_small/47172959.jpg",
    "ban_tcg": "",
    "ban_ocg": "",
    "ban_goat": "",
    "staple": "",
    "views": 118885,
    "viewsweek": 26,
    "upvotes": 0,
    "downvotes": 0,
    "formats": "TCG|OCG|Master Duel",
    "treated_as": "",
    "tcg_date": "2024-02-08",
    "ocg_date": "2023-10-28",
    "konami_id": 19493,
    "has_effect": 1
  },
  {
    "id": 31764700,
    "name": "Yubel - The Ultimate Nightmare",
    "type": "Effect Monster",
    "desc": "Cannot be Normal Summoned or Set. Must be Special Summoned by \"Yubel - Terror Incarnate\", and cannot be Special Summoned by other ways. This card cannot be destroyed by battle. You take no Battle Damage from battles involving this card. At the end of the Damage Step, if this face-up Attack Position card battles an opponent's monster: Inflict damage equal to that monster's ATK to your opponent, also destroy that monster.",
    "atk": 0,
    "def": 0,
    "level": 12,
    "race": "Fiend",
    "attribute": "DARK",
    "scale": "",
    "archetype": "Yubel",
    "linkval": "",
    "linkmarkers": "",
    "image_url": "https://images.ygoprodeck.com/images/cards/31764700.jpg",
    "image_url_small": "https://images.ygoprodeck.com/images/cards_small/31764700.jpg",
    "ban_tcg": "",
    "ban_ocg": "",
    "ban_goat": "",
    "staple": "",
    "views": 165652,
    "viewsweek": 0,
    "upvotes": 15,
    "downvotes": 8,
    "formats": "Duel Links|Edison|TCG|OCG|Master Duel",
    "treated_as": "",
    "tcg_date": "2008-01-26",
    "ocg_date": "2007-11-23",
    "konami_id": 7411,
    "has_effect": 1
  },
  {
    "id": 72700231,
    "name": "Yuki-Musume, the Ice Mayakashi",
    "type": "Effect Monster",
    "desc": "If you control a \"Mayakashi\" card, other than \"Yuki-Musume, the Ice Mayakashi\" while this card is in your hand or GY: You can Special Summon this card, then send 1 Zombie monster from your Deck to the GY. You can only use this effect of \"Yuki-Musume, the Ice Mayakashi\" once per turn. You cannot Special Summon monsters from the Extra Deck, except \"Mayakashi\" monsters.",
    "atk": 0,
    "def": 1900,
    "level": 1,
    "race": "Zombie",
    "attribute": "WATER",
    "scale": "",
    "archetype": "Mayakashi",
    "linkval": "",
    "linkmarkers": "",
    "image_url": "https://images.ygoprodeck.com/images/cards/72700231.jpg",
    "image_url_small": "https://images.ygoprodeck.com/images/cards_small/72700231.jpg",
    "ban_tcg": "",
    "ban_ocg": "",
    "ban_goat": "",
    "staple": "",
    "views": 142727,
    "viewsweek": 0,
    "upvotes": 2,
    "downvotes": 0,
    "formats": "Duel Links|Common Charity|TCG|OCG|Master Duel",
    "treated_as": "",
    "tcg_date": "2019-03-07",
    "ocg_date": "2019-01-12",
    "konami_id": 14266,
    "has_effect": 1
  },
  {
    "id": 2645637,
    "name": "Yuki-Onna, the Absolute Zero Mayakashi",
    "type": "Link Monster",
    "desc": "2+ Zombie monsters\nYou can only control 1 \"Yuki-Onna, the Absolute Zero Mayakashi\". Negate any activated effects of your opponent's banished monsters. If a monster is Special Summoned from the GY, or a monster effect is activated in the GY (except during the Damage Step): You can target 1 other face-up monster on the field; change its ATK to 0, and if you do, negate its effects. You can use this effect of \"Yuki-Onna, the Absolute Zero Mayakashi\" up to twice per turn.",
    "atk": 2900,
    "def": "",
    "level": "",
    "race": "Zombie",
    "attribute": "WATER",
    "scale": "",
    "archetype": "Mayakashi",
    "linkval": 4,
    "linkmarkers": "['Left', 'Bottom-Left', 'Bottom-Right', 'Right']",
    "image_url": "https://images.ygoprodeck.com/images/cards/2645637.jpg",
    "image_url_small": "https://images.ygoprodeck.com/images/cards_small/2645637.jpg",
    "ban_tcg": "",
    "ban_ocg": "",
    "ban_goat": "",
    "staple": "",
    "views": 253868,
    "viewsweek": 0,
    "upvotes": 13,
    "downvotes": 2,
    "formats": "TCG|OCG|Master Duel",
    "treated_as": "",
    "tcg_date": "2020-03-19",
    "ocg_date": "2019-11-23",
    "konami_id": 14948,
    "has_effect": 1
  },
  {
    "id": 66870733,
    "name": "Yuki-Onna, the Ice Mayakashi",
    "type": "Link Monster",
    "desc": "2 \"Mayakashi\" monsters\nYou can only control 1 \"Yuki-Onna, the Ice Mayakashi\". While this card points to a Synchro Monster(s), your opponent's monsters cannot target this card for attacks. If a Synchro Monster(s) in your possession is destroyed by battle or an opponent's card effect while this card is on the field: You can target 1 face-up monster on the field; its ATK/DEF become half its current ATK/DEF until the end of this turn. You can only use this effect of \"Yuki-Onna, the Ice Mayakashi\" once per turn.",
    "atk": 1900,
    "def": "",
    "level": "",
    "race": "Zombie",
    "attribute": "WATER",
    "scale": "",
    "archetype": "Mayakashi",
    "linkval": 2,
    "linkmarkers": "['Bottom-Left', 'Bottom-Right']",
    "image_url": "https://images.ygoprodeck.com/images/cards/66870733.jpg",
    "image_url_small": "https://images.ygoprodeck.com/images/cards_small/66870733.jpg",
    "ban_tcg": "",
    "ban_ocg": "",
    "ban_goat": "",
    "staple": "",
    "views": 124266,
    "viewsweek": 0,
    "upvotes": 11,
    "downvotes": 1,
    "formats": "TCG|OCG|Master Duel",
    "treated_as": "",
    "tcg_date": "2018-11-15",
    "ocg_date": "2018-08-04",
    "konami_id": 14043,
    "has_effect": 1
  },
  {
    "id": 36114945,
    "name": "Yuki-Onna, the Icicle Mayakashi",
    "type": "Link Monster",
    "desc": "2+ Zombie monsters\nYou can only control 1 \"Yuki-Onna, the Icicle Mayakashi\". You can only use each of the following effects of \"Yuki-Onna, the Icicle Mayakashi\" once per turn. If this card is Special Summoned: You can target 1 Effect Monster your opponent controls; negate its effects. (Quick Effect): You can banish this card from your GY; Special Summon 1 of your Zombie Synchro Monsters that is banished or in your GY.",
    "atk": 2400,
    "def": "",
    "level": "",
    "race": "Zombie",
    "attribute": "WATER",
    "scale": "",
    "archetype": "Mayakashi",
    "linkval": 3,
    "linkmarkers": "['Bottom-Left', 'Bottom-Right', 'Bottom']",
    "image_url": "https://images.ygoprodeck.com/images/cards/36114945.jpg",
    "image_url_small": "https://images.ygoprodeck.com/images/cards_small/36114945.jpg",
    "ban_tcg": "",
    "ban_ocg": "",
    "ban_goat": "",
    "staple": "",
    "views": 53903,
    "viewsweek": 0,
    "upvotes": 9,
    "downvotes": 0,
    "formats": "TCG|OCG|Master Duel",
    "treated_as": "",
    "tcg_date": "2022-11-03",
    "ocg_date": "2021-12-04",
    "konami_id": 17035,
    "has_effect": 1
  }
]